{
  "metadata": {
    "doc_hash": "5171e185",
    "saved_at": "2025-05-26T06:32:25.731523",
    "source_url": "http://www.moe.gov.cn/jyb_xxgk/xxgk_jyta/jyta_xwb/201712/"
  },
  "content": {
    "文件标题": "教育部对十二届全国人大五次会议第7235号建议的答复",
    "副标题": "",
    "正文内容": "您提出的“关于在‘双一流’建设中加大对地方高校扶持的建议”收悉，现答复如下：\n一、关于“双一流”建设\n建设世界一流大学和一流学科，是党中央、国务院作出的重大战略决策。根据《统筹推进世界一流大学和一流学科建设总体方案》和《统筹推进世界一流大学和一流学科建设实施办法（暂行）》要求，按照稳中求进、继承创新、改革发展的工作原则，经“双一流”建设专家委员会遴选推荐，教育部、财政部、国家发展改革委研究并报国务院批准，确定了“双一流”建设高校及建设学科名单，支持一批地方高校建设世界一流大学和一流学科。名单即将于近日向社会公布。\n以学科为基础，服务国家重大战略与区域发展布局，破除身份固化，分类建设，实行开放竞争，激发建设活力，是“双一流”的重要制度设计。教育部将对接国家重大战略部署，统筹推动各类高水平大学和优势学科的建设。\n二、关于高校人才队伍建设\n一直以来，教育部高度重视地方高校的发展，把加强地方高校高层次人才队伍建设作为推动地方高校整体实力提升的一项重要的基础性工程来抓。\n在“长江学者奖励计划”实施过程中，把地方高校摆在重要位置，强化政策导向，采取切实措施，坚持同等条件下给予地方高校倾斜支持，充分发挥长江学者等高层次人才在促进地方高校人才队伍建设中的示范和带动作用。一是面向全国高校实施，充分发挥学校的用人主体作用，鼓励学校按需设岗、公开招聘、择优申报，鼓励和支持地方高校优秀人才积极参与竞争。二是在坚持“同平台、同条件、同标准”评审的同时，优先支持对区域经济社会发展贡献大、学科具有特色优势的地方高校人选，采取倾斜政策，设立专门名额，遴选支持地方高校人选。\n近年来，地方高校特聘教授人选比例持续上升，2016年比例达到19%，其中有4人从教育部直属高校应聘到地方高校工作。\n感谢您对教育工作的关心和支持。\n教 育 部\n2017年9月19日",
    "附件": []
  }
}