{
  "metadata": {
    "doc_hash": "5d7174a5",
    "saved_at": "2025-05-26T06:32:28.136124",
    "source_url": "http://www.moe.gov.cn/jyb_xxgk/xxgk_jyta/jyta_gjs/201901/"
  },
  "content": {
    "文件标题": "关于政协十三届全国委员会第一次会议第3790号（教育类347号）提案答复的函",
    "副标题": "",
    "正文内容": "您提出的《关于发挥香港高校优势，协同两地大学扩大在一带一路国家的影响的提案》收悉，经商国务院港澳办，现答复如下：\n建设世界一流大学和一流学科是国家作出的重大战略决策。国务院发布的《统筹推进世界一流大学和一流学科建设总体方案》和教育部、财政部、国家发展改革委联合印发的《统筹推进世界一流大学和一流学科建设实施办法（暂行）》，都明确提出要推进国际交流合作，切实提高我国高等教育的国际竞争力和话语权，树立中国大学的良好品牌和形象。\n关于内地大学与香港大学合作，寻求在一带一路国家中推动相关专业领域的发展，并在当地该专业领域中取得参与制定相关标准和准则的资格的建议，具有较强的建设性和可行性。一直以来，我部高度重视推动内地大学与香港大学的交流与合作，支持香港大学加入2015年成立的“中国大学创新创业教育联盟”，支持粤港澳大学联盟、京港大学联盟等交流平台的建设，推动内地“双一流”大学与香港大学间优质教育资源的共享，在课程共研、共建、共享和成绩转换、学分互认、联合培养等方面都取得良好成效。\n下一步，我部将继续鼓励和支持内地大学和香港大学开展更频繁、更深入的实质性合作，以粤港澳大湾区建设为契机，加强优势学科和新兴学科建设，实现高水平大学优势互补，建设世界一流大学集群，积极参与国际教育规则制定、国家教育教学评估认证，加快教育对外开放步伐，切实提高我国高等教育的国际竞争力和话语权，不断提升我国高等教育的影响力。\n感谢您对教育工作的关心和支持！\n教 育 部\n2018年9月19日",
    "附件": []
  }
}